{"PREVALENCE_BY_GENDER_AGE_YEAR":{"TRELLIS_NAME":"10-19","SERIES_NAME":"FEMALE","X_CALENDAR_YEAR":2005,"Y_PREVALENCE_1000PP":0.40451},"PREVALENCE_BY_MONTH":{"X_CALENDAR_MONTH":["200508","200606","200608","200806","200807","201007","201106","201107","201207","201307","201407"],"Y_PREVALENCE_1000PP":[0.06662,0.02583,0.04364,0.03541,0.02884,0.02174,0.01914,0.04492,0.02035,0.05954,0.03751]},"CONDITIONS_BY_TYPE":{"CONCEPT_NAME":["Primary Condition","Secondary Condition"],"COUNT_VALUE":[143,56]},"AGE_AT_FIRST_DIAGNOSIS":{"CATEGORY":["FEMALE","MALE"],"MIN_VALUE":[1,1],"P10_VALUE":[15,11],"P25_VALUE":[23,17],"MEDIAN_VALUE":[49,35],"P75_VALUE":[74,60],"P90_VALUE":[85,71],"MAX_VALUE":[107,99]}}
