{"PREVALENCE_BY_GENDER_AGE_YEAR":{"TRELLIS_NAME":["60-69","50-59"],"SERIES_NAME":["FEMALE","MALE"],"X_CALENDAR_YEAR":[2011,2014],"Y_PREVALENCE_1000PP":[0.24895,0.35051]},"PREVALENCE_BY_MONTH":{"X_CALENDAR_MONTH":["201409","200703","201406","200411","201407"],"Y_PREVALENCE_1000PP":[0.03029,0.02763,0.02722,0.03121,0.02813]},"LENGTH_OF_ERA":{"CATEGORY":"Length of era","MIN_VALUE":1,"P10_VALUE":1,"P25_VALUE":1,"MEDIAN_VALUE":1,"P75_VALUE":1,"P90_VALUE":12,"MAX_VALUE":63},"AGE_AT_FIRST_DIAGNOSIS":{"CATEGORY":["MALE","FEMALE"],"MIN_VALUE":[1,1],"P10_VALUE":[16,17],"P25_VALUE":[37,25],"MEDIAN_VALUE":[55,50],"P75_VALUE":[65,63],"P90_VALUE":[72,70],"MAX_VALUE":[90,89]}}
