{"PREVALENCE_BY_GENDER_AGE_YEAR":{"TRELLIS_NAME":["40-49","50-59","60-69","50-59","60-69","60-69","60-69","70-79","60-69"],"SERIES_NAME":["MALE","MALE","MALE","MALE","MALE","MALE","MALE","FEMALE","MALE"],"X_CALENDAR_YEAR":[2004,2004,2004,2005,2005,2013,2014,2014,2015],"Y_PREVALENCE_1000PP":[0.50835,0.66523,0.85211,0.51972,0.45921,0.37558,0.39575,0.38632,0.57078]},"PREVALENCE_BY_MONTH":{"X_CALENDAR_MONTH":["201501","201504","200412","201310","201003","201311","201308","200404","200403","200504","200411","200602","201412","200509"],"Y_PREVALENCE_1000PP":[0.03916,0.05895,0.04017,0.02702,0.02166,0.02359,0.02263,0.05933,0.08878,0.04499,0.04161,0.02313,0.04794,0.03692]},"LENGTH_OF_ERA":{"CATEGORY":"Length of era","MIN_VALUE":1,"P10_VALUE":1,"P25_VALUE":1,"MEDIAN_VALUE":1,"P75_VALUE":1,"P90_VALUE":1,"MAX_VALUE":78},"AGE_AT_FIRST_DIAGNOSIS":{"CATEGORY":["MALE","FEMALE"],"MIN_VALUE":[0,0],"P10_VALUE":[29,25],"P25_VALUE":[46,43],"MEDIAN_VALUE":[59,62],"P75_VALUE":[69,77],"P90_VALUE":[78,84],"MAX_VALUE":[96,97]}}
