{"PREVALENCE_BY_GENDER_AGE_YEAR":{"TRELLIS_NAME":["50-59","30-39","50-59","40-49","50-59","50-59","50-59","60-69"],"SERIES_NAME":["FEMALE","FEMALE","FEMALE","FEMALE","FEMALE","MALE","FEMALE","FEMALE"],"X_CALENDAR_YEAR":[2008,2008,2009,2009,2010,2010,2011,2011],"Y_PREVALENCE_1000PP":[0.31364,0.16102,0.30764,0.22504,0.30802,0.29129,0.34908,0.24895]},"PREVALENCE_BY_MONTH":{"X_CALENDAR_MONTH":["200804","201304","200903","200906","201104","201008","201210"],"Y_PREVALENCE_1000PP":[0.01942,0.02883,0.01873,0.01867,0.019,0.01866,0.03104]},"LENGTH_OF_ERA":{"CATEGORY":"Length of era","MIN_VALUE":1,"P10_VALUE":1,"P25_VALUE":1,"MEDIAN_VALUE":1,"P75_VALUE":1,"P90_VALUE":27,"MAX_VALUE":126},"AGE_AT_FIRST_DIAGNOSIS":{"CATEGORY":["FEMALE","MALE"],"MIN_VALUE":[13,16],"P10_VALUE":[28,24],"P25_VALUE":[39,33],"MEDIAN_VALUE":[51,47],"P75_VALUE":[59,56],"P90_VALUE":[68,61],"MAX_VALUE":[86,84]}}
