{"PREVALENCE_BY_GENDER_AGE_YEAR":{"TRELLIS_NAME":"70-79","SERIES_NAME":"MALE","X_CALENDAR_YEAR":2011,"Y_PREVALENCE_1000PP":0.44673},"PREVALENCE_BY_MONTH":{"X_CALENDAR_MONTH":["200609","200505","200407","201307","200506","200401","200405"],"Y_PREVALENCE_1000PP":[0.02529,0.02637,0.04487,0.02233,0.02583,0.11911,0.04526]},"LENGTH_OF_ERA":{"CATEGORY":"Length of era","MIN_VALUE":1,"P10_VALUE":1,"P25_VALUE":1,"MEDIAN_VALUE":1,"P75_VALUE":4,"P90_VALUE":31,"MAX_VALUE":158},"AGE_AT_FIRST_DIAGNOSIS":{"CATEGORY":["MALE","FEMALE"],"MIN_VALUE":[2,1],"P10_VALUE":[25,14],"P25_VALUE":[41,40],"MEDIAN_VALUE":[60,54],"P75_VALUE":[72,67],"P90_VALUE":[78,81],"MAX_VALUE":[87,95]}}
