{"PREVALENCE_BY_GENDER_AGE_YEAR":{"TRELLIS_NAME":"50-59","SERIES_NAME":"MALE","X_CALENDAR_YEAR":2006,"Y_PREVALENCE_1000PP":0.34562},"PREVALENCE_BY_MONTH":{"X_CALENDAR_MONTH":["200606","200801"],"Y_PREVALENCE_1000PP":[0.03321,0.01964]},"PROCEDURES_BY_TYPE":{"CONCEPT_NAME":"Primary Procedure","COUNT_VALUE":114},"AGE_AT_FIRST_OCCURRENCE":{"CATEGORY":["FEMALE","MALE"],"MIN_VALUE":[15,5],"P10_VALUE":[20,31],"P25_VALUE":[37,52],"MEDIAN_VALUE":[52,64],"P75_VALUE":[63,74],"P90_VALUE":[78,83],"MAX_VALUE":[81,87]}}
