{"PREVALENCE_BY_GENDER_AGE_YEAR":{"TRELLIS_NAME":["20-29","20-29","30-39","10-19","0-9","40-49","10-19"],"SERIES_NAME":["FEMALE","MALE","MALE","FEMALE","FEMALE","MALE","MALE"],"X_CALENDAR_YEAR":[2007,2007,2007,2007,2007,2007,2007],"Y_PREVALENCE_1000PP":[0.21737,0.33574,0.50235,0.38217,0.28252,0.43891,0.84778]},"PREVALENCE_BY_MONTH":{"X_CALENDAR_MONTH":["200702","200703","200705","200706","200707","200708","200709"],"Y_PREVALENCE_1000PP":[0.02445,0.02763,0.03069,0.03056,0.04733,0.04708,0.02344]},"PROCEDURES_BY_TYPE":{"CONCEPT_NAME":"Primary Procedure","COUNT_VALUE":186},"AGE_AT_FIRST_OCCURRENCE":{"CATEGORY":["MALE","FEMALE"],"MIN_VALUE":[3,1],"P10_VALUE":[12,7],"P25_VALUE":[14,15],"MEDIAN_VALUE":[22,25],"P75_VALUE":[35,48],"P90_VALUE":[45,63],"MAX_VALUE":[78,83]}}
