{"PREVALENCE_BY_GENDER_AGE_YEAR":{"TRELLIS_NAME":["10-19","0-9","60-69","10-19","0-9","60-69"],"SERIES_NAME":["MALE","MALE","MALE","MALE","MALE","MALE"],"X_CALENDAR_YEAR":[2005,2006,2006,2007,2007,2007],"Y_PREVALENCE_1000PP":[0.39989,0.22799,0.40056,0.32969,0.46275,0.36726]},"PREVALENCE_BY_MONTH":{"X_CALENDAR_MONTH":["200703","200708"],"Y_PREVALENCE_1000PP":[0.02763,0.02354]},"PROCEDURES_BY_TYPE":{"CONCEPT_NAME":"Primary Procedure","COUNT_VALUE":138},"AGE_AT_FIRST_OCCURRENCE":{"CATEGORY":"MALE","MIN_VALUE":0,"P10_VALUE":3,"P25_VALUE":9,"MEDIAN_VALUE":35,"P75_VALUE":61,"P90_VALUE":69,"MAX_VALUE":88}}
