{"PREVALENCE_BY_GENDER_AGE_YEAR":{"TRELLIS_NAME":["50-59","60-69"],"SERIES_NAME":["MALE","FEMALE"],"X_CALENDAR_YEAR":[2006,2006],"Y_PREVALENCE_1000PP":[0.40323,0.30187]},"PREVALENCE_BY_MONTH":{"X_CALENDAR_MONTH":["200607","200609"],"Y_PREVALENCE_1000PP":[0.02202,0.02529]},"PROCEDURES_BY_TYPE":{"CONCEPT_NAME":"Primary Procedure","COUNT_VALUE":108},"AGE_AT_FIRST_OCCURRENCE":{"CATEGORY":["FEMALE","MALE"],"MIN_VALUE":[17,16],"P10_VALUE":[28,19],"P25_VALUE":[48,44],"MEDIAN_VALUE":[59,51],"P75_VALUE":[68,63],"P90_VALUE":[71,73],"MAX_VALUE":[82,80]}}
