{"PREVALENCE_BY_GENDER_AGE_YEAR":{"TRELLIS_NAME":["40-49","60-69"],"SERIES_NAME":["FEMALE","MALE"],"X_CALENDAR_YEAR":[2005,2007],"Y_PREVALENCE_1000PP":[0.25976,0.36726]},"PREVALENCE_BY_MONTH":{"X_CALENDAR_MONTH":["200505","200703","200801"],"Y_PREVALENCE_1000PP":[0.03516,0.02418,0.01964]},"PROCEDURES_BY_TYPE":{"CONCEPT_NAME":"Primary Procedure","COUNT_VALUE":126},"AGE_AT_FIRST_OCCURRENCE":{"CATEGORY":["FEMALE","MALE"],"MIN_VALUE":[17,7],"P10_VALUE":[24,28],"P25_VALUE":[36,39],"MEDIAN_VALUE":[46,51],"P75_VALUE":[60,61],"P90_VALUE":[68,69],"MAX_VALUE":[74,73]}}
