{"PREVALENCE_BY_GENDER_AGE_YEAR":{"TRELLIS_NAME":["50-59","60-69","60-69","70-79","50-59","70-79"],"SERIES_NAME":["FEMALE","FEMALE","MALE","MALE","MALE","FEMALE"],"X_CALENDAR_YEAR":[2011,2011,2011,2011,2011,2011],"Y_PREVALENCE_1000PP":[0.59343,0.5394,0.36114,0.67009,0.2949,0.43325]},"PREVALENCE_BY_MONTH":{"X_CALENDAR_MONTH":["201102","201103","201104","201105"],"Y_PREVALENCE_1000PP":[0.0599,0.06294,0.02533,0.07619]},"PROCEDURES_BY_TYPE":{"CONCEPT_NAME":"Primary Procedure","COUNT_VALUE":163},"AGE_AT_FIRST_OCCURRENCE":{"CATEGORY":["FEMALE","MALE"],"MIN_VALUE":[2,0],"P10_VALUE":[27,28],"P25_VALUE":[43,41],"MEDIAN_VALUE":[56,61],"P75_VALUE":[65,73],"P90_VALUE":[74,79],"MAX_VALUE":[92,86]}}
